dynamicprompts/__init__.py
dynamicprompts/constants.py
dynamicprompts/enums.py
dynamicprompts/jinja_extensions.py
dynamicprompts/py.typed
dynamicprompts/sampling_context.py
dynamicprompts/sampling_result.py
dynamicprompts/types.py
dynamicprompts/utils.py
dynamicprompts/commands/__init__.py
dynamicprompts/commands/base.py
dynamicprompts/commands/literal_command.py
dynamicprompts/commands/sequence_command.py
dynamicprompts/commands/variable_commands.py
dynamicprompts/commands/variant_command.py
dynamicprompts/commands/wildcard_command.py
dynamicprompts/commands/wrap_command.py
dynamicprompts/generators/__init__.py
dynamicprompts/generators/attentiongenerator.py
dynamicprompts/generators/batched_combinatorial.py
dynamicprompts/generators/combinatorial.py
dynamicprompts/generators/dummygenerator.py
dynamicprompts/generators/feelinglucky.py
dynamicprompts/generators/jinjagenerator.py
dynamicprompts/generators/magicprompt.py
dynamicprompts/generators/promptgenerator.py
dynamicprompts/generators/randomprompt.py
dynamicprompts/parser/__init__.py
dynamicprompts/parser/config.py
dynamicprompts/parser/parse.py
dynamicprompts/samplers/__init__.py
dynamicprompts/samplers/base.py
dynamicprompts/samplers/combinatorial.py
dynamicprompts/samplers/command_collection.py
dynamicprompts/samplers/cycle.py
dynamicprompts/samplers/random.py
dynamicprompts/samplers/utils.py
dynamicprompts/wildcards/__init__.py
dynamicprompts/wildcards/item.py
dynamicprompts/wildcards/types.py
dynamicprompts/wildcards/utils.py
dynamicprompts/wildcards/values.py
dynamicprompts/wildcards/wildcard_manager.py
dynamicprompts/wildcards/collection/__init__.py
dynamicprompts/wildcards/collection/base.py
dynamicprompts/wildcards/collection/list.py
dynamicprompts/wildcards/collection/structured.py
dynamicprompts/wildcards/collection/text_file.py
dynamicprompts/wildcards/tree/__init__.py
dynamicprompts/wildcards/tree/build.py
dynamicprompts/wildcards/tree/node.py
dynamicprompts/wildcards/tree/tree.py
dynamicprompts-0.31.0.dist-info/METADATA
dynamicprompts-0.31.0.dist-info/WHEEL
dynamicprompts-0.31.0.dist-info/licenses/LICENSE
dynamicprompts-0.31.0.dist-info/RECORD
